sylva-0.1.2.dist-info/METADATA
sylva-0.1.2.dist-info/WHEEL
sylva-0.1.2.dist-info/entry_points.txt
sylva-0.1.2.dist-info/licenses/COPYING
sylva/__init__.py
sylva/cache.py
sylva/collector.py
sylva/config.py
sylva/console.py
sylva/data/__scm_version__.py
sylva/data/pgp.json
sylva/data/pgp.schema.json
sylva/data/site_patterns.json
sylva/data/site_patterns.schema.json
sylva/easy_logger.py
sylva/errors.py
sylva/handler.py
sylva/helpers/__init__.py
sylva/helpers/generic.py
sylva/helpers/pattern_match.py
sylva/helpers/proxy.py
sylva/integrations/__init__.py
sylva/integrations/endato.py
sylva/integrations/exposed_lol.py
sylva/integrations/intelx.py
sylva/integrations/intelxapi.py
sylva/integrations/proxynova.py
sylva/integrations/veriphone.py
sylva/modules/__init__.py
sylva/modules/github.py
sylva/modules/pgp.py
sylva/modules/sherlock.py
sylva/modules/voter.py
sylva/modules/voter_regions/USA.py
sylva/modules/voter_regions/__init__.py
sylva/types.py
sylva-0.1.2.dist-info/RECORD
