Metadata-Version: 2.1
Name: sylva
Version: 0.1.2
Summary: Identity discovery simplified
Home-page: https://sylva.pfeister.dev
Author-Email: Paul Pfeister <code@pfeister.dev>
License: AGPL-3.0-or-later
Project-URL: Homepage, https://sylva.pfeister.dev
Project-URL: Repository, https://github.com/ppfeister/sylva
Project-URL: Bug-tracker, https://github.com/ppfeister/sylva/issues
Requires-Python: >=3.10
Requires-Dist: sherlock-project>=0.15.0
Requires-Dist: platformdirs>=4.2.2
Requires-Dist: requests>=2.28.0
Requires-Dist: pandas>=2.2.2
Requires-Dist: colorama>=0.4.6
Requires-Dist: phonenumbers>=8.13.40
Requires-Dist: tldextract>=3.5.0
Requires-Dist: BeautifulSoup4>=4.12.3
Requires-Dist: aiohttp>=3.9.5
Requires-Dist: bottle>=0.12.25
Requires-Dist: certifi>=2023.5.7
Requires-Dist: charset-normalizer>=3.3.2
Requires-Dist: click>=8.1.7
Requires-Dist: cssselect>=1.1.0
Requires-Dist: et-xmlfile>=1.1.0
Requires-Dist: filelock>=3.15.4
Requires-Dist: func-timeout>=4.3.5
Requires-Dist: idna>=3.7
Requires-Dist: lxml>=4.9.3
Requires-Dist: openpyxl>=3.1.2
Requires-Dist: pefile==2023.2.7; platform_system == "Windows"
Requires-Dist: prometheus-client>=0.17.1
Requires-Dist: psutil>=5.9.5
Requires-Dist: requests-file>=1.5.1
Requires-Dist: urllib3>=1.26.19
Requires-Dist: waitress>=2.1.2
Requires-Dist: websocket-client>=1.3.3
Requires-Dist: websockets>=11.0.3
Requires-Dist: xvfbwrapper>=0.2.9; platform_system != "Windows"
Requires-Dist: cryptography>=3.3.2
Requires-Dist: pyasn1>=0.5.1
Requires-Dist: mkdocs-material>=9.5.30; extra == "mkdocs"
Requires-Dist: mkdocs-minify-plugin>=0.8.0; extra == "mkdocs"
Requires-Dist: mkdocs-git-revision-date-plugin>=0.3.2; extra == "mkdocs"
Requires-Dist: mkdocstrings[python]>=0.25.2; extra == "mkdocs"
Provides-Extra: mkdocs
